sphinxext/toptranslators.py
sphinxext_toptranslators-0.1.3.dist-info/LICENSE.md
sphinxext_toptranslators-0.1.3.dist-info/METADATA
sphinxext_toptranslators-0.1.3.dist-info/WHEEL
sphinxext_toptranslators-0.1.3.dist-info/top_level.txt
sphinxext_toptranslators-0.1.3.dist-info/RECORD
